saavn/__init__.py
saavn/__main__.py
saavn/cli.py
saavn/client.py
saavn/routes.py
saavn/saavn.py
saavn/models/__init__.py
saavn/models/album.py
saavn/models/artist.py
saavn/models/playlist.py
saavn/models/track.py
saavn_py-0.1.3.dist-info/METADATA
saavn_py-0.1.3.dist-info/WHEEL
saavn_py-0.1.3.dist-info/entry_points.txt
saavn_py-0.1.3.dist-info/licenses/LICENSE
saavn_py-0.1.3.dist-info/RECORD
