Metadata-Version: 2.3
Name: saavn.py
Version: 0.1.3
Summary: A Python client for the JioSaavn API
Project-URL: Homepage, https://github.com/0xhimangshu/jiosaavn-main
Author-email: 0xhimangshu <saikiahimangshu1256@gmail.com>
Classifier: License :: OSI Approved :: MIT License
Classifier: Operating System :: OS Independent
Classifier: Programming Language :: Python :: 3
Requires-Python: >=3.7
Requires-Dist: h2
Requires-Dist: httpx
Requires-Dist: pynput
Requires-Dist: rich
